pygments_styles/__init__.py
pygments_styles/_gruvbox.py
pygments_styles/andromeeda.py
pygments_styles/aurora_x.py
pygments_styles/ayu_dark.py
pygments_styles/ayu_light.py
pygments_styles/ayu_mirage.py
pygments_styles/catppuccin_frappe.py
pygments_styles/catppuccin_latte.py
pygments_styles/catppuccin_macchiato.py
pygments_styles/catppuccin_mocha.py
pygments_styles/dark_plus.py
pygments_styles/everforest_dark.py
pygments_styles/everforest_light.py
pygments_styles/github_dark_default.py
pygments_styles/github_dark_dimmed.py
pygments_styles/github_dark_high_contrast.py
pygments_styles/github_light_default.py
pygments_styles/github_light_high_contrast.py
pygments_styles/gruvbox_dark_hard.py
pygments_styles/gruvbox_dark_medium.py
pygments_styles/gruvbox_dark_soft.py
pygments_styles/gruvbox_light_hard.py
pygments_styles/gruvbox_light_medium.py
pygments_styles/gruvbox_light_soft.py
pygments_styles/laserwave.py
pygments_styles/laserwave_high_contrast.py
pygments_styles/light_plus.py
pygments_styles/one_dark_pro.py
pygments_styles/one_light.py
pygments_styles/plastic.py
pygments_styles-0.2.0.dist-info/licenses/LICENSE
pygments_styles-0.2.0.dist-info/METADATA
pygments_styles-0.2.0.dist-info/WHEEL
pygments_styles-0.2.0.dist-info/entry_points.txt
pygments_styles-0.2.0.dist-info/top_level.txt
pygments_styles-0.2.0.dist-info/RECORD
