Metadata-Version: 2.4
Name: pygments-styles
Version: 0.2.0
Summary: A curated collection of Pygments styles based on VS Code themes.
Author-email: Hsiaoming Yang <me@lepture.com>
License: BSD-3-Clause
Project-URL: Source, https://github.com/lepture/pygments-styles
Project-URL: Homepage, https://pygments-styles.org/
Project-URL: Sponsors, https://github.com/sponsors/lepture
Classifier: Development Status :: 4 - Beta
Classifier: Intended Audience :: Developers
Classifier: Intended Audience :: Education
Classifier: License :: OSI Approved :: BSD License
Classifier: Operating System :: OS Independent
Classifier: Programming Language :: Python
Classifier: Programming Language :: Python :: 3
Classifier: Programming Language :: Python :: 3.9
Classifier: Programming Language :: Python :: 3.10
Classifier: Programming Language :: Python :: 3.11
Classifier: Programming Language :: Python :: 3.12
Classifier: Programming Language :: Python :: 3.13
Classifier: Programming Language :: Python :: Implementation :: CPython
Classifier: Programming Language :: Python :: Implementation :: PyPy
Classifier: Topic :: Utilities
Requires-Python: >=3.9
License-File: LICENSE
Requires-Dist: pygments
Dynamic: license-file
